streamlit_elements_fluence/__init__.py
streamlit_elements_fluence/version.py
streamlit_elements_fluence/core/__init__.py
streamlit_elements_fluence/core/callback.py
streamlit_elements_fluence/core/element.py
streamlit_elements_fluence/core/exceptions.py
streamlit_elements_fluence/core/frame.py
streamlit_elements_fluence/core/jscallback.py
streamlit_elements_fluence/core/render.py
streamlit_elements_fluence/frontend/.babelrc
streamlit_elements_fluence/frontend/.eslintrc.json
streamlit_elements_fluence/frontend/.gitignore
streamlit_elements_fluence/frontend/next-env.d.ts
streamlit_elements_fluence/frontend/next.config.js
streamlit_elements_fluence/frontend/package-lock.json
streamlit_elements_fluence/frontend/package.json
streamlit_elements_fluence/frontend/tsconfig.json
streamlit_elements_fluence/frontend/build/404.html
streamlit_elements_fluence/frontend/build/index.html
streamlit_elements_fluence/frontend/build/_next/static/180OSX_QJ6cHoiebEm8eF/_buildManifest.js
streamlit_elements_fluence/frontend/build/_next/static/180OSX_QJ6cHoiebEm8eF/_middlewareManifest.js
streamlit_elements_fluence/frontend/build/_next/static/180OSX_QJ6cHoiebEm8eF/_ssgManifest.js
streamlit_elements_fluence/frontend/build/_next/static/chunks/1034.246fd272afec35b5.js
streamlit_elements_fluence/frontend/build/_next/static/chunks/1041.a74079fdb5006c53.js
streamlit_elements_fluence/frontend/build/_next/static/chunks/1109.4aa2cbb0ff7c55bc.js
streamlit_elements_fluence/frontend/build/_next/static/chunks/1146.8361d71abb9cec97.js
streamlit_elements_fluence/frontend/build/_next/static/chunks/1261.e9f21eca88059303.js
streamlit_elements_fluence/frontend/build/_next/static/chunks/1397.1eca889ed99178b5.js
streamlit_elements_fluence/frontend/build/_next/static/chunks/1400-3f5e93777d9d6603.js
streamlit_elements_fluence/frontend/build/_next/static/chunks/1448.9b60f095f5d914df.js
streamlit_elements_fluence/frontend/build/_next/static/chunks/1477.bb0fcd4dfa5a638e.js
streamlit_elements_fluence-0.1.4.dist-info/LICENSE
streamlit_elements_fluence-0.1.4.dist-info/METADATA
streamlit_elements_fluence-0.1.4.dist-info/WHEEL
streamlit_elements_fluence-0.1.4.dist-info/top_level.txt
streamlit_elements_fluence-0.1.4.dist-info/RECORD
