Metadata-Version: 2.1
Name: streamlit-elements-fluence
Version: 0.1.4
Summary: React Components for Streamlit.
Home-page: https://fluence.world
Author: aschofield
License: MIT
Platform: UNKNOWN
Requires-Python: >=3.6
License-File: LICENSE
Requires-Dist: streamlit (>=1.4.0)
